an_em_design/__init__.py
an_em_design/run.py
an_em_design/server.py
an_em_design/server_run_back.py
anmotordesign/__init__.py
anmotordesign/run.py
anmotordesign/server.py
anmotordesign/server_run_back.py
anmotordesign-0.1a0.dist-info/LICENSE.txt
anmotordesign-0.1a0.dist-info/METADATA
anmotordesign-0.1a0.dist-info/WHEEL
anmotordesign-0.1a0.dist-info/top_level.txt
anmotordesign-0.1a0.dist-info/RECORD
