Metadata-Version: 2.1
Name: anmotordesign
Version: 0.1a0
Summary: Electrical Machines Design Automation by Ansys Maxwell Script
Home-page: https://github.com/MarkWengSTR/ansys-maxwell-EM-design-online
Author: Mark Weng
Author-email: bskin0330@gmail.com
License: UNKNOWN
Platform: UNKNOWN
Classifier: Programming Language :: Python :: 3
Classifier: License :: OSI Approved :: MIT License
Classifier: Operating System :: OS Independent
Requires-Python: >=3.6
Requires-Dist: setuptools
Requires-Dist: pywin32 (==227)
Requires-Dist: ramda (==0.5.5)
Requires-Dist: six (==1.13.0)
Requires-Dist: functional-pipeline (==0.3.1)
Requires-Dist: ipdb (==0.12.3)
Requires-Dist: Flask (==1.1.2)
Requires-Dist: Flask-Cors (==3.0.8)
Requires-Dist: pandas (==1.0.1)
Requires-Dist: numpy (==1.18.1)
Requires-Dist: requests (==2.24.0)
